{
  "cycle_number": 5918,
  "timestamp": "2025-10-11T00:10:33.923584",
  "tests": {
    "production_endpoints": {
      "frontend": {
        "status_code": 520,
        "response_time": 0.491898,
        "status": "unhealthy"
      },
      "api": {
        "status": "error",
        "error": "[Errno 32] Broken pipe"
      },
      "health": {
        "status_code": 520,
        "response_time": 0.404827,
        "status": "unhealthy"
      }
    },
    "knowledge_graph": {
      "status": "success",
      "insights_count": 10,
      "query_time": 0.006285
    },
    "gcp_infrastructure": {
      "status": "healthy",
      "pods_running": true,
      "services_available": true,
      "load_balancer": "active"
    },
    "monitoring": {
      "status": "active",
      "prometheus": "running",
      "grafana": "accessible"
    }
  },
  "cycle_duration": 1.7315678596496582,
  "status": "completed"
}