{
  "cycle_number": 5870,
  "timestamp": "2025-10-10T23:22:04.744940",
  "tests": {
    "production_endpoints": {
      "frontend": {
        "status_code": 520,
        "response_time": 0.41792,
        "status": "unhealthy"
      },
      "api": {
        "status_code": 520,
        "response_time": 0.536855,
        "status": "unhealthy"
      },
      "health": {
        "status_code": 520,
        "response_time": 0.495384,
        "status": "unhealthy"
      }
    },
    "knowledge_graph": {
      "status": "success",
      "insights_count": 10,
      "query_time": 0.006542
    },
    "gcp_infrastructure": {
      "status": "healthy",
      "pods_running": true,
      "services_available": true,
      "load_balancer": "active"
    },
    "monitoring": {
      "status": "active",
      "prometheus": "running",
      "grafana": "accessible"
    }
  },
  "cycle_duration": 1.7901830673217773,
  "status": "completed"
}